lab3/Submitted/ex4/fulladder.v
module fulladder( sum, co, a, b, ci);

  input   a, b, ci;
  output  sum, co;
  wire    w1, w2, w3;

  xor g0(w1, a, b);
  xor g1(sum, w1, ci);
  and g2(w2, w1, ci);
  and g3(w3, a, b);
  or  g4(co, w2, w3);

endmodule

lab3/Submitted/ex5/add4.v
module  add4( sum, co, a, b, ci);

  input   [3:0] a, b;
  input   ci;
  output  [3:0] sum;
  output  co;

  wire co0, co1, co2;

  fulladder fa0(sum[0], co0, a[0], b[0], ci);
  fulladder fa1(sum[1], co1, a[1], b[1], co0);
  fulladder fa2(sum[2], co2, a[2], b[2], co1);
  fulladder fa3(sum[3], co,  a[3], b[3], co2);
endmodule

lab3/ex5/addsub.v
module	addsub( result, operand_a, operand_b, mode );

	input	[3:0]	operand_a, operand_b;
	input	mode;
	output	[3:0]	result;
	wire co;
	wire	[3:0]	xor_b;

	xor	g0(xor_b[0], operand_b[0], mode);
   	xor	g1(xor_b[1], operand_b[1], mode);	
        xor	g2(xor_b[2], operand_b[2], mode);
       	xor	g3(xor_b[3], operand_b[3], mode);
   
	add4	m1(
		.sum(result),
		.co(co),
		.a(operand_a),	 
		.b(xor_b),	
		.ci(mode)
	);	
endmodule

lab3/Submitted/ex5/addsub_tb.v
module	addsub_tb;
	
	// for DUT port connection
	reg					mode;
	reg 	[3:0]	operand_a, operand_b;
	wire	[3:0] result;
	wire co;
	
	// for pattern generation
	integer			a, b, expect, error_num, t;
	reg					overflow;
	wire	[3:0]	expect_out = expect[3:0];	// compare "expect_out" with "result"

	// FILL here
        addsub addsub(result, operand_a, operand_b, mode);
   

	// give stimulus pattern
	initial begin
	error_num = 0;

	$dumpfile("waves.vcd");
	$dumpvars;

	$display( "\nTest subtraction mode." );
	#10 mode = 1'b1;
	
	for( a=-8; a<=7; a=a+1 ) begin
		for( b=-8; b<=7; b=b+1 ) begin
			
			operand_a = a[3:0];
			operand_b = b[3:0];
			expect = a - b;
	
			#1;
			if( expect >= -8 && expect <= 7 ) begin
				overflow = 1'b0;
				if( expect[3:0] !== result ) begin
					error_num = error_num + 1;
					$display( "Error(%d):(%d)-(%d) Expect(%b) Output(%b)", error_num[9:0], a, b, expect[3:0], result );
				end
			end	else begin
				overflow = 1'b1;
			end
	
			#1;
		end
	end

	$display( "\nTest addition mode." );
	mode = 1'b0;
	
	for( a=-8; a<=7; a=a+1 ) begin
		for( b=-8; b<=7; b=b+1 ) begin
			
			operand_a = a[3:0];
			operand_b = b[3:0];
			expect = a + b;
	
			#1;
			if( expect >= -8 && expect <= 7 ) begin
				overflow = 1'b0;
				if( expect[3:0] !== result ) begin
					error_num = error_num + 1;
					$display( "Error(%d):(%d)+(%d) Expect(%b) Output(%b)", error_num[9:0], a, b, expect[3:0], result );
				end
			end	else begin
				overflow = 1'b1;
			end
	
			#1;
		end
	end
	
	if( error_num==0 )
		$display( "\nPass all test\n" );
	else
		$display( "\nFail, error number = %d\n", error_num );
	
	#10 $finish;
	end

endmodule

lab3/ex5/waves.vcd
$date
    Apr 22, 2013  20:48:18
$end
$version
    TOOL:	ncsim	11.10-p001
$end
$timescale
    1 ns
$end

$scope module addsub_tb $end
$var reg       1 !    mode  $end
$var reg       4 "    operand_a [3:0] $end
$var reg       4 #    operand_b [3:0] $end
$var wire      1 $    result [3] $end
$var wire      1 %    result [2] $end
$var wire      1 &    result [1] $end
$var wire      1 '    result [0] $end
$var wire      1 (    co  $end
$var integer  32 )    a  $end
$var integer  32 *    b  $end
$var integer  32 +    expect  $end
$var integer  32 ,    error_num  $end
$var integer  32 -    t  $end
$var reg       1 .    overflow  $end
$var wire      4 /    expect_out [3:0] $end

$scope module addsub $end
$var wire      1 0    operand_a [3] $end
$var wire      1 1    operand_a [2] $end
$var wire      1 2    operand_a [1] $end
$var wire      1 3    operand_a [0] $end
$var wire      1 4    operand_b [3] $end
$var wire      1 5    operand_b [2] $end
$var wire      1 6    operand_b [1] $end
$var wire      1 7    operand_b [0] $end
$var wire      1 8    mode  $end
$var wire      1 $    result [3] $end
$var wire      1 %    result [2] $end
$var wire      1 &    result [1] $end
$var wire      1 '    result [0] $end
$var wire      1 9    co  $end
$var wire      1 :    xor_b [3] $end
$var wire      1 ;    xor_b [2] $end
$var wire      1 <    xor_b [1] $end
$var wire      1 =    xor_b [0] $end

$scope module m1 $end
$var wire      1 0    a [3] $end
$var wire      1 1    a [2] $end
$var wire      1 2    a [1] $end
$var wire      1 3    a [0] $end
$var wire      1 :    b [3] $end
$var wire      1 ;    b [2] $end
$var wire      1 <    b [1] $end
$var wire      1 =    b [0] $end
$var wire      1 8    ci  $end
$var wire      1 $    sum [3] $end
$var wire      1 %    sum [2] $end
$var wire      1 &    sum [1] $end
$var wire      1 '    sum [0] $end
$var wire      1 9    co  $end
$var wire      1 >    co0  $end
$var wire      1 ?    co1  $end
$var wire      1 @    co2  $end

$scope module fa0 $end
$var wire      1 3    a  $end
$var wire      1 =    b  $end
$var wire      1 8    ci  $end
$var wire      1 '    sum  $end
$var wire      1 >    co  $end
$var wire      1 A    w1  $end
$var wire      1 B    w2  $end
$var wire      1 C    w3  $end
$upscope $end


$scope module fa1 $end
$var wire      1 2    a  $end
$var wire      1 <    b  $end
$var wire      1 >    ci  $end
$var wire      1 &    sum  $end
$var wire      1 ?    co  $end
$var wire      1 D    w1  $end
$var wire      1 E    w2  $end
$var wire      1 F    w3  $end
$upscope $end


$scope module fa2 $end
$var wire      1 1    a  $end
$var wire      1 ;    b  $end
$var wire      1 ?    ci  $end
$var wire      1 %    sum  $end
$var wire      1 @    co  $end
$var wire      1 G    w1  $end
$var wire      1 H    w2  $end
$var wire      1 I    w3  $end
$upscope $end


$scope module fa3 $end
$var wire      1 0    a  $end
$var wire      1 :    b  $end
$var wire      1 @    ci  $end
$var wire      1 $    sum  $end
$var wire      1 9    co  $end
$var wire      1 J    w1  $end
$var wire      1 K    w2  $end
$var wire      1 L    w3  $end
$upscope $end

$upscope $end

$upscope $end

$upscope $end

$enddefinitions $end
$dumpvars
x!
bx "
bx #
x$
x%
x&
x'
z(
bx )
bx *
bx +
b0 ,
bx -
x.
bx /
x0
x1
x2
x3
x4
x5
x6
x7
x8
x9
x:
x;
x<
x=
x>
x?
x@
xA
xB
xC
xD
xE
xF
xG
xH
xI
xJ
xK
xL
$end
#10
1!
b11111111111111111111111111111000 )
b11111111111111111111111111111000 *
b1000 "
b1000 #
b0 +
b0 /
14
05
06
07
10
01
02
03
18
0:
1;
1<
1=
0C
0F
0I
1A
1D
1G
1J
0L
0'
1B
1>
0&
1E
1?
0%
1H
1@
0$
1K
19
#11
0.
#12
b11111111111111111111111111111001 *
b1001 #
b11111111111111111111111111111111 +
b1111 /
17
0=
0A
1'
0B
0>
1&
0E
0?
1%
0H
0@
1$
0K
09
#14
b11111111111111111111111111111010 *
b1010 #
b11111111111111111111111111111110 +
b1110 /
16
07
1=
0<
0D
1A
0'
1B
1&
1>
#16
b11111111111111111111111111111011 *
b1011 #
b11111111111111111111111111111101 +
b1101 /
17
0=
0A
1'
0B
0>
0&
#18
b11111111111111111111111111111100 *
b1100 #
b11111111111111111111111111111100 +
b1100 /
15
06
07
1=
1<
0;
0G
1D
1A
0'
1B
0&
1%
1>
1E
1?
#20
b11111111111111111111111111111101 *
b1101 #
b11111111111111111111111111111011 +
b1011 /
17
0=
0A
1'
0B
0>
1&
0E
0?
0%
#22
b11111111111111111111111111111110 *
b1110 #
b11111111111111111111111111111010 +
b1010 /
16
07
1=
0<
0D
1A
0'
1B
1&
1>
#24
b11111111111111111111111111111111 *
b1111 #
b11111111111111111111111111111001 +
b1001 /
17
0=
0A
1'
0B
0>
0&
#26
b0 *
b0 #
b11111111111111111111111111111000 +
b1000 /
04
05
06
07
1=
1<
1;
1:
0J
1L
1G
1D
1A
0'
1B
0&
0%
19
1$
1>
1E
1?
1H
1@
#28
b1 *
b1 #
b11111111111111111111111111110111 +
b111 /
17
0=
0A
1'
0B
0>
1&
0E
0?
1%
0H
0@
0$
#29
1.
#30
b10 *
b10 #
b11111111111111111111111111110110 +
b110 /
16
07
1=
0<
0D
1A
0'
1B
1&
1>
#32
b11 *
b11 #
b11111111111111111111111111110101 +
b101 /
17
0=
0A
1'
0B
0>
0&
#34
b100 *
b100 #
b11111111111111111111111111110100 +
b100 /
15
06
07
1=
1<
0;
0G
1D
1A
0'
1B
0&
1%
1>
1E
1?
#36
b101 *
b101 #
b11111111111111111111111111110011 +
b11 /
17
0=
0A
1'
0B
0>
1&
0E
0?
0%
#38
b110 *
b110 #
b11111111111111111111111111110010 +
b10 /
16
07
1=
0<
0D
1A
0'
1B
1&
1>
#40
b111 *
b111 #
b11111111111111111111111111110001 +
b1 /
17
0=
0A
1'
0B
0>
0&
#42
b1000 *
b11111111111111111111111111111001 )
b11111111111111111111111111111000 *
b1001 "
b1000 #
b1 +
14
05
06
07
13
0A
1=
1<
1;
0:
1J
0L
1G
1D
1C
1>
0%
19
0$
1E
1?
1H
1@
1K
#43
0.
#44
b11111111111111111111111111111001 *
b1001 #
b0 +
b0 /
17
0=
1A
0C
1>
0'
1B
#46
b11111111111111111111111111111010 *
b1010 #
b11111111111111111111111111111111 +
b1111 /
16
07
1=
0<
0D
0A
1C
1'
0B
1&
0E
0?
1%
0H
0@
1$
0K
09
#48
b11111111111111111111111111111011 *
b1011 #
b11111111111111111111111111111110 +
b1110 /
17
0=
1A
0C
1>
0'
1B
#50
b11111111111111111111111111111100 *
b1100 #
b11111111111111111111111111111101 +
b1101 /
15
06
07
1=
1<
0;
0G
1D
0A
1C
1'
0B
0&
1E
1%
1?
#52
b11111111111111111111111111111101 *
b1101 #
b11111111111111111111111111111100 +
b1100 /
17
0=
1A
0C
1>
0'
1B
#54
b11111111111111111111111111111110 *
b1110 #
b11111111111111111111111111111011 +
b1011 /
16
07
1=
0<
0D
0A
1C
1'
0B
1&
0E
0?
0%
#56
b11111111111111111111111111111111 *
b1111 #
b11111111111111111111111111111010 +
b1010 /
17
0=
1A
0C
1>
0'
1B
#58
b0 *
b0 #
b11111111111111111111111111111001 +
b1001 /
04
05
06
07
1=
1<
1;
1:
0J
1L
1G
1D
0A
1C
1'
0B
0&
1E
0%
19
1$
1?
1H
1@
#60
b1 *
b1 #
b11111111111111111111111111111000 +
b1000 /
17
0=
1A
0C
1>
0'
1B
#62
b10 *
b10 #
b11111111111111111111111111110111 +
b111 /
16
07
1=
0<
0D
0A
1C
1'
0B
1&
0E
0?
1%
0H
0@
0$
#63
1.
#64
b11 *
b11 #
b11111111111111111111111111110110 +
b110 /
17
0=
1A
0C
1>
0'
1B
#66
b100 *
b100 #
b11111111111111111111111111110101 +
b101 /
15
06
07
1=
1<
0;
0G
1D
0A
1C
1'
0B
0&
1E
1%
1?
#68
b101 *
b101 #
b11111111111111111111111111110100 +
b100 /
17
0=
1A
0C
1>
0'
1B
#70
b110 *
b110 #
b11111111111111111111111111110011 +
b11 /
16
07
1=
0<
0D
0A
1C
1'
0B
1&
0E
0?
0%
#72
b111 *
b111 #
b11111111111111111111111111110010 +
b10 /
17
0=
1A
0C
1>
0'
1B
#74
b1000 *
b11111111111111111111111111111010 )
b11111111111111111111111111111000 *
b1010 "
b1000 #
b10 +
14
05
06
07
12
03
1A
0D
1=
1<
1;
0:
1J
0L
1G
1F
1?
19
0$
1H
1@
1K
#75
0.
#76
b11111111111111111111111111111001 *
b1001 #
b1 +
b1 /
17
0=
0A
1'
0B
0>
0&
#78
b11111111111111111111111111111010 *
b1010 #
b0 +
b0 /
16
07
1=
0<
1D
0F
1A
0'
1B
1?
0&
0%
1H
1>
1E
1@
0$
1K
19
#80
b11111111111111111111111111111011 *
b1011 #
b11111111111111111111111111111111 +
b1111 /
17
0=
0A
1'
0B
0>
1&
0E
0?
1%
0H
0@
1$
0K
09
#82
b11111111111111111111111111111100 *
b1100 #
b11111111111111111111111111111110 +
b1110 /
15
06
07
1=
1<
0;
0G
0D
1F
1A
0'
1B
1?
1&
1>
#84
b11111111111111111111111111111101 *
b1101 #
b11111111111111111111111111111101 +
b1101 /
17
0=
0A
1'
0B
0>
0&
#86
b11111111111111111111111111111110 *
b1110 #
b11111111111111111111111111111100 +
b1100 /
16
07
1=
0<
1D
0F
1A
0'
1B
1?
0&
1%
1>
1E
#88
b11111111111111111111111111111111 *
b1111 #
b11111111111111111111111111111011 +
b1011 /
17
0=
0A
1'
0B
0>
1&
0E
0?
0%
#90
b0 *
b0 #
b11111111111111111111111111111010 +
b1010 /
04
05
06
07
1=
1<
1;
1:
0J
1L
1G
0D
1F
1A
0'
1B
1?
1&
19
1$
1H
1>
1@
#92
b1 *
b1 #
b11111111111111111111111111111001 +
b1001 /
17
0=
0A
1'
0B
0>
0&
#94
b10 *
b10 #
b11111111111111111111111111111000 +
b1000 /
16
07
1=
0<
1D
0F
1A
0'
1B
1?
0&
0%
1H
1>
1E
1@
1$
#96
b11 *
b11 #
b11111111111111111111111111110111 +
b111 /
17
0=
0A
1'
0B
0>
1&
0E
0?
1%
0H
0@
0$
#97
1.
#98
b100 *
b100 #
b11111111111111111111111111110110 +
b110 /
15
06
07
1=
1<
0;
0G
0D
1F
1A
0'
1B
1?
1&
1>
#100
b101 *
b101 #
b11111111111111111111111111110101 +
b101 /
17
0=
0A
1'
0B
0>
0&
#102
b110 *
b110 #
b11111111111111111111111111110100 +
b100 /
16
07
1=
0<
1D
0F
1A
0'
1B
1?
0&
1%
1>
1E
#104
b111 *
b111 #
b11111111111111111111111111110011 +
b11 /
17
0=
0A
1'
0B
0>
1&
0E
0?
0%
#106
b1000 *
b11111111111111111111111111111011 )
b11111111111111111111111111111000 *
b1011 "
b1000 #
b11 +
14
05
06
07
13
0A
1=
1<
1;
0:
1J
0L
1G
0D
1F
1C
1>
1?
19
0$
1H
1@
1K
#107
0.
#108
b11111111111111111111111111111001 *
b1001 #
b10 +
b10 /
17
0=
1A
0C
1>
0'
1B
#110
b11111111111111111111111111111010 *
b1010 #
b1 +
b1 /
16
07
1=
0<
1D
0F
0A
1C
1'
0B
1?
0&
1E
#112
b11111111111111111111111111111011 *
b1011 #
b0 +
b0 /
17
0=
1A
0C
1>
0'
1B
#114
b11111111111111111111111111111100 *
b1100 #
b11111111111111111111111111111111 +
b1111 /
15
06
07
1=
1<
0;
0G
0D
1F
0A
1C
1'
0B
1&
0E
1%
0H
0@
1$
0K
09
#116
b11111111111111111111111111111101 *
b1101 #
b11111111111111111111111111111110 +
b1110 /
17
0=
1A
0C
1>
0'
1B
#118
b11111111111111111111111111111110 *
b1110 #
b11111111111111111111111111111101 +
b1101 /
16
07
1=
0<
1D
0F
0A
1C
1'
0B
1?
0&
1E
#120
b11111111111111111111111111111111 *
b1111 #
b11111111111111111111111111111100 +
b1100 /
17
0=
1A
0C
1>
0'
1B
#122
b0 *
b0 #
b11111111111111111111111111111011 +
b1011 /
04
05
06
07
1=
1<
1;
1:
0J
1L
1G
0D
1F
0A
1C
1'
0B
1&
0E
0%
1H
19
1$
1@
#124
b1 *
b1 #
b11111111111111111111111111111010 +
b1010 /
17
0=
1A
0C
1>
0'
1B
#126
b10 *
b10 #
b11111111111111111111111111111001 +
b1001 /
16
07
1=
0<
1D
0F
0A
1C
1'
0B
1?
0&
1E
#128
b11 *
b11 #
b11111111111111111111111111111000 +
b1000 /
17
0=
1A
0C
1>
0'
1B
#130
b100 *
b100 #
b11111111111111111111111111110111 +
b111 /
15
06
07
1=
1<
0;
0G
0D
1F
0A
1C
1'
0B
1&
0E
1%
0H
0@
0$
#131
1.
#132
b101 *
b101 #
b11111111111111111111111111110110 +
b110 /
17
0=
1A
0C
1>
0'
1B
#134
b110 *
b110 #
b11111111111111111111111111110101 +
b101 /
16
07
1=
0<
1D
0F
0A
1C
1'
0B
1?
0&
1E
#136
b111 *
b111 #
b11111111111111111111111111110100 +
b100 /
17
0=
1A
0C
1>
0'
1B
#138
b1000 *
b11111111111111111111111111111100 )
b11111111111111111111111111111000 *
b1100 "
b1000 #
b100 +
14
05
06
07
11
02
03
1A
1D
0G
1=
1<
1;
0:
1J
0L
1I
1@
19
1K
#139
0.
#140
b11111111111111111111111111111001 *
b1001 #
b11 +
b11 /
17
0=
0A
1'
0B
0>
1&
0E
0?
0%
#142
b11111111111111111111111111111010 *
b1010 #
b10 +
b10 /
16
07
1=
0<
0D
1A
0'
1B
1&
1>
#144
b11111111111111111111111111111011 *
b1011 #
b1 +
b1 /
17
0=
0A
1'
0B
0>
0&
#146
b11111111111111111111111111111100 *
b1100 #
b0 +
b0 /
15
06
07
1=
1<
0;
1G
0I
1D
1A
0'
1B
0&
1@
0%
0$
1K
1>
1E
19
1?
1H
#148
b11111111111111111111111111111101 *
b1101 #
b11111111111111111111111111111111 +
b1111 /
17
0=
0A
1'
0B
0>
1&
0E
0?
1%
0H
0@
1$
0K
09
#150
b11111111111111111111111111111110 *
b1110 #
b11111111111111111111111111111110 +
b1110 /
16
07
1=
0<
0D
1A
0'
1B
1&
1>
#152
b11111111111111111111111111111111 *
b1111 #
b11111111111111111111111111111101 +
b1101 /
17
0=
0A
1'
0B
0>
0&
#154
b0 *
b0 #
b11111111111111111111111111111100 +
b1100 /
04
05
06
07
1=
1<
1;
1:
0J
1L
0G
1I
1D
1A
0'
1B
0&
1@
1%
19
1>
1E
1?
#156
b1 *
b1 #
b11111111111111111111111111111011 +
b1011 /
17
0=
0A
1'
0B
0>
1&
0E
0?
0%
#158
b10 *
b10 #
b11111111111111111111111111111010 +
b1010 /
16
07
1=
0<
0D
1A
0'
1B
1&
1>
#160
b11 *
b11 #
b11111111111111111111111111111001 +
b1001 /
17
0=
0A
1'
0B
0>
0&
#162
b100 *
b100 #
b11111111111111111111111111111000 +
b1000 /
15
06
07
1=
1<
0;
1G
0I
1D
1A
0'
1B
0&
1@
0%
1$
1>
1E
1?
1H
#164
b101 *
b101 #
b11111111111111111111111111110111 +
b111 /
17
0=
0A
1'
0B
0>
1&
0E
0?
1%
0H
0@
0$
#165
1.
#166
b110 *
b110 #
b11111111111111111111111111110110 +
b110 /
16
07
1=
0<
0D
1A
0'
1B
1&
1>
#168
b111 *
b111 #
b11111111111111111111111111110101 +
b101 /
17
0=
0A
1'
0B
0>
0&
#170
b1000 *
b11111111111111111111111111111101 )
b11111111111111111111111111111000 *
b1101 "
b1000 #
b101 +
14
05
06
07
13
0A
1=
1<
1;
0:
1J
0L
0G
1I
1D
1C
1>
1@
1%
19
1K
1E
1?
#171
0.
#172
b11111111111111111111111111111001 *
b1001 #
b100 +
b100 /
17
0=
1A
0C
1>
0'
1B
#174
b11111111111111111111111111111010 *
b1010 #
b11 +
b11 /
16
07
1=
0<
0D
0A
1C
1'
0B
1&
0E
0?
0%
#176
b11111111111111111111111111111011 *
b1011 #
b10 +
b10 /
17
0=
1A
0C
1>
0'
1B
#178
b11111111111111111111111111111100 *
b1100 #
b1 +
b1 /
15
06
07
1=
1<
0;
1G
0I
1D
0A
1C
1'
0B
0&
1E
1@
0%
0$
1K
1?
1H
19
#180
b11111111111111111111111111111101 *
b1101 #
b0 +
b0 /
17
0=
1A
0C
1>
0'
1B
#182
b11111111111111111111111111111110 *
b1110 #
b11111111111111111111111111111111 +
b1111 /
16
07
1=
0<
0D
0A
1C
1'
0B
1&
0E
0?
1%
0H
0@
1$
0K
09
#184
b11111111111111111111111111111111 *
b1111 #
b11111111111111111111111111111110 +
b1110 /
17
0=
1A
0C
1>
0'
1B
#186
b0 *
b0 #
b11111111111111111111111111111101 +
b1101 /
04
05
06
07
1=
1<
1;
1:
0J
1L
0G
1I
1D
0A
1C
1'
0B
0&
1E
1@
1%
19
1?
#188
b1 *
b1 #
b11111111111111111111111111111100 +
b1100 /
17
0=
1A
0C
1>
0'
1B
#190
b10 *
b10 #
b11111111111111111111111111111011 +
b1011 /
16
07
1=
0<
0D
0A
1C
1'
0B
1&
0E
0?
0%
#192
b11 *
b11 #
b11111111111111111111111111111010 +
b1010 /
17
0=
1A
0C
1>
0'
1B
#194
b100 *
b100 #
b11111111111111111111111111111001 +
b1001 /
15
06
07
1=
1<
0;
1G
0I
1D
0A
1C
1'
0B
0&
1E
1@
0%
1$
1?
1H
#196
b101 *
b101 #
b11111111111111111111111111111000 +
b1000 /
17
0=
1A
0C
1>
0'
1B
#198
b110 *
b110 #
b11111111111111111111111111110111 +
b111 /
16
07
1=
0<
0D
0A
1C
1'
0B
1&
0E
0?
1%
0H
0@
0$
#199
1.
#200
b111 *
b111 #
b11111111111111111111111111110110 +
b110 /
17
0=
1A
0C
1>
0'
1B
#202
b1000 *
b11111111111111111111111111111110 )
b11111111111111111111111111111000 *
b1110 "
b1000 #
b110 +
14
05
06
07
12
03
1A
0D
1=
1<
1;
0:
1J
0L
0G
1I
1F
1?
1@
19
1K
#203
0.
#204
b11111111111111111111111111111001 *
b1001 #
b101 +
b101 /
17
0=
0A
1'
0B
0>
0&
#206
b11111111111111111111111111111010 *
b1010 #
b100 +
b100 /
16
07
1=
0<
1D
0F
1A
0'
1B
1?
0&
1%
1>
1E
#208
b11111111111111111111111111111011 *
b1011 #
b11 +
b11 /
17
0=
0A
1'
0B
0>
1&
0E
0?
0%
#210
b11111111111111111111111111111100 *
b1100 #
b10 +
b10 /
15
06
07
1=
1<
0;
1G
0I
0D
1F
1A
0'
1B
1?
1&
1@
0$
1K
1H
1>
19
#212
b11111111111111111111111111111101 *
b1101 #
b1 +
b1 /
17
0=
0A
1'
0B
0>
0&
#214
b11111111111111111111111111111110 *
b1110 #
b0 +
b0 /
16
07
1=
0<
1D
0F
1A
0'
1B
1?
0&
0%
1H
1>
1E
1@
0$
1K
19
#216
b11111111111111111111111111111111 *
b1111 #
b11111111111111111111111111111111 +
b1111 /
17
0=
0A
1'
0B
0>
1&
0E
0?
1%
0H
0@
1$
0K
09
#218
b0 *
b0 #
b11111111111111111111111111111110 +
b1110 /
04
05
06
07
1=
1<
1;
1:
0J
1L
0G
1I
0D
1F
1A
0'
1B
1?
1&
1@
19
1>
#220
b1 *
b1 #
b11111111111111111111111111111101 +
b1101 /
17
0=
0A
1'
0B
0>
0&
#222
b10 *
b10 #
b11111111111111111111111111111100 +
b1100 /
16
07
1=
0<
1D
0F
1A
0'
1B
1?
0&
1%
1>
1E
#224
b11 *
b11 #
b11111111111111111111111111111011 +
b1011 /
17
0=
0A
1'
0B
0>
1&
0E
0?
0%
#226
b100 *
b100 #
b11111111111111111111111111111010 +
b1010 /
15
06
07
1=
1<
0;
1G
0I
0D
1F
1A
0'
1B
1?
1&
1@
1$
1H
1>
#228
b101 *
b101 #
b11111111111111111111111111111001 +
b1001 /
17
0=
0A
1'
0B
0>
0&
#230
b110 *
b110 #
b11111111111111111111111111111000 +
b1000 /
16
07
1=
0<
1D
0F
1A
0'
1B
1?
0&
0%
1H
1>
1E
1@
1$
#232
b111 *
b111 #
b11111111111111111111111111110111 +
b111 /
17
0=
0A
1'
0B
0>
1&
0E
0?
1%
0H
0@
0$
#233
1.
#234
b1000 *
b11111111111111111111111111111111 )
b11111111111111111111111111111000 *
b1111 "
b1000 #
b111 +
14
05
06
07
13
0A
1=
1<
1;
0:
1J
0L
0G
1I
0D
1F
1C
1>
1?
1@
19
1K
#235
0.
#236
b11111111111111111111111111111001 *
b1001 #
b110 +
b110 /
17
0=
1A
0C
1>
0'
1B
#238
b11111111111111111111111111111010 *
b1010 #
b101 +
b101 /
16
07
1=
0<
1D
0F
0A
1C
1'
0B
1?
0&
1E
#240
b11111111111111111111111111111011 *
b1011 #
b100 +
b100 /
17
0=
1A
0C
1>
0'
1B
#242
b11111111111111111111111111111100 *
b1100 #
b11 +
b11 /
15
06
07
1=
1<
0;
1G
0I
0D
1F
0A
1C
1'
0B
1&
0E
1@
0%
1H
#244
b11111111111111111111111111111101 *
b1101 #
b10 +
b10 /
17
0=
1A
0C
1>
0'
1B
#246
b11111111111111111111111111111110 *
b1110 #
b1 +
b1 /
16
07
1=
0<
1D
0F
0A
1C
1'
0B
1?
0&
1E
#248
b11111111111111111111111111111111 *
b1111 #
b0 +
b0 /
17
0=
1A
0C
1>
0'
1B
#250
b0 *
b0 #
b11111111111111111111111111111111 +
b1111 /
04
05
06
07
1=
1<
1;
1:
0J
1L
0G
1I
0D
1F
0A
1C
1'
0B
1&
0E
1%
0H
1$
0K
#252
b1 *
b1 #
b11111111111111111111111111111110 +
b1110 /
17
0=
1A
0C
1>
0'
1B
#254
b10 *
b10 #
b11111111111111111111111111111101 +
b1101 /
16
07
1=
0<
1D
0F
0A
1C
1'
0B
1?
0&
1E
#256
b11 *
b11 #
b11111111111111111111111111111100 +
b1100 /
17
0=
1A
0C
1>
0'
1B
#258
b100 *
b100 #
b11111111111111111111111111111011 +
b1011 /
15
06
07
1=
1<
0;
1G
0I
0D
1F
0A
1C
1'
0B
1&
0E
1@
0%
1H
#260
b101 *
b101 #
b11111111111111111111111111111010 +
b1010 /
17
0=
1A
0C
1>
0'
1B
#262
b110 *
b110 #
b11111111111111111111111111111001 +
b1001 /
16
07
1=
0<
1D
0F
0A
1C
1'
0B
1?
0&
1E
#264
b111 *
b111 #
b11111111111111111111111111111000 +
b1000 /
17
0=
1A
0C
1>
0'
1B
#266
b1000 *
b0 )
b11111111111111111111111111111000 *
b0 "
b1000 #
b1000 +
14
05
06
07
00
01
02
03
1A
1D
1G
0J
0L
1=
1<
1;
0:
09
#267
1.
#268
b11111111111111111111111111111001 *
b1001 #
b111 +
b111 /
17
0=
0A
1'
0B
0>
1&
0E
0?
1%
0H
0@
0$
#269
0.
#270
b11111111111111111111111111111010 *
b1010 #
b110 +
b110 /
16
07
1=
0<
0D
1A
0'
1B
1&
1>
#272
b11111111111111111111111111111011 *
b1011 #
b101 +
b101 /
17
0=
0A
1'
0B
0>
0&
#274
b11111111111111111111111111111100 *
b1100 #
b100 +
b100 /
15
06
07
1=
1<
0;
0G
1D
1A
0'
1B
0&
1%
1>
1E
1?
#276
b11111111111111111111111111111101 *
b1101 #
b11 +
b11 /
17
0=
0A
1'
0B
0>
1&
0E
0?
0%
#278
b11111111111111111111111111111110 *
b1110 #
b10 +
b10 /
16
07
1=
0<
0D
1A
0'
1B
1&
1>
#280
b11111111111111111111111111111111 *
b1111 #
b1 +
b1 /
17
0=
0A
1'
0B
0>
0&
#282
b0 *
b0 #
b0 +
b0 /
04
05
06
07
1=
1<
1;
1:
1J
1G
1D
1A
0'
1B
0&
0%
0$
1>
1E
1?
1H
1@
1K
19
#284
b1 *
b1 #
b11111111111111111111111111111111 +
b1111 /
17
0=
0A
1'
0B
0>
1&
0E
0?
1%
0H
0@
1$
0K
09
#286
b10 *
b10 #
b11111111111111111111111111111110 +
b1110 /
16
07
1=
0<
0D
1A
0'
1B
1&
1>
#288
b11 *
b11 #
b11111111111111111111111111111101 +
b1101 /
17
0=
0A
1'
0B
0>
0&
#290
b100 *
b100 #
b11111111111111111111111111111100 +
b1100 /
15
06
07
1=
1<
0;
0G
1D
1A
0'
1B
0&
1%
1>
1E
1?
#292
b101 *
b101 #
b11111111111111111111111111111011 +
b1011 /
17
0=
0A
1'
0B
0>
1&
0E
0?
0%
#294
b110 *
b110 #
b11111111111111111111111111111010 +
b1010 /
16
07
1=
0<
0D
1A
0'
1B
1&
1>
#296
b111 *
b111 #
b11111111111111111111111111111001 +
b1001 /
17
0=
0A
1'
0B
0>
0&
#298
b1000 *
b1 )
b11111111111111111111111111111000 *
b1 "
b1000 #
b1001 +
14
05
06
07
13
0A
1=
1<
1;
0:
0J
1G
1D
1C
1>
0%
1$
1E
1?
1H
1@
#299
1.
#300
b11111111111111111111111111111001 *
b1001 #
b1000 +
b1000 /
17
0=
1A
0C
1>
0'
1B
#302
b11111111111111111111111111111010 *
b1010 #
b111 +
b111 /
16
07
1=
0<
0D
0A
1C
1'
0B
1&
0E
0?
1%
0H
0@
0$
#303
0.
#304
b11111111111111111111111111111011 *
b1011 #
b110 +
b110 /
17
0=
1A
0C
1>
0'
1B
#306
b11111111111111111111111111111100 *
b1100 #
b101 +
b101 /
15
06
07
1=
1<
0;
0G
1D
0A
1C
1'
0B
0&
1E
1%
1?
#308
b11111111111111111111111111111101 *
b1101 #
b100 +
b100 /
17
0=
1A
0C
1>
0'
1B
#310
b11111111111111111111111111111110 *
b1110 #
b11 +
b11 /
16
07
1=
0<
0D
0A
1C
1'
0B
1&
0E
0?
0%
#312
b11111111111111111111111111111111 *
b1111 #
b10 +
b10 /
17
0=
1A
0C
1>
0'
1B
#314
b0 *
b0 #
b1 +
b1 /
04
05
06
07
1=
1<
1;
1:
1J
1G
1D
0A
1C
1'
0B
0&
1E
0%
0$
1?
1H
1@
1K
19
#316
b1 *
b1 #
b0 +
b0 /
17
0=
1A
0C
1>
0'
1B
#318
b10 *
b10 #
b11111111111111111111111111111111 +
b1111 /
16
07
1=
0<
0D
0A
1C
1'
0B
1&
0E
0?
1%
0H
0@
1$
0K
09
#320
b11 *
b11 #
b11111111111111111111111111111110 +
b1110 /
17
0=
1A
0C
1>
0'
1B
#322
b100 *
b100 #
b11111111111111111111111111111101 +
b1101 /
15
06
07
1=
1<
0;
0G
1D
0A
1C
1'
0B
0&
1E
1%
1?
#324
b101 *
b101 #
b11111111111111111111111111111100 +
b1100 /
17
0=
1A
0C
1>
0'
1B
#326
b110 *
b110 #
b11111111111111111111111111111011 +
b1011 /
16
07
1=
0<
0D
0A
1C
1'
0B
1&
0E
0?
0%
#328
b111 *
b111 #
b11111111111111111111111111111010 +
b1010 /
17
0=
1A
0C
1>
0'
1B
#330
b1000 *
b10 )
b11111111111111111111111111111000 *
b10 "
b1000 #
b1010 +
14
05
06
07
12
03
1A
0D
1=
1<
1;
0:
0J
1G
1F
1?
1$
1H
1@
#331
1.
